{
  "roleId": "coding.specifier",
  "packId": "coding",
  "contractVersion": "v1alpha1",
  "responsibility": "Turn an accepted bridge or scoped request into a reviewable spec boundary for the coding mainline.",
  "readableArtifactRoles": [
    "spec-bridge",
    "spec"
  ],
  "writableArtifactRoles": [
    "spec"
  ],
  "triggerableNodes": [
    "coding.bridge-intake",
    "coding.specify"
  ],
  "handoffScope": [
    "in-pack",
    "cross-pack"
  ],
  "policyRefs": [
    "policies/input-completeness.md",
    "policies/authoring-review.md"
  ]
}
